{"type":"FeatureCollection","road-info":{"t":0,"l":[["道央道",0],["札樽道",0],["道東道",0],["十勝オホーツク道",0]]},"features":[{"type":"Feature","properties":{"cs":"21","r":"十勝オホーツク道","rn":"35000202","d":"上り","i":"訓子府ＩＣ付近→訓子府ＩＣ","c":"工事","rd":"１車線規制","a":"情報なし","p":[[152.93771,56.18656]],"l":"t","lo":260,"pd":["十勝オホーツク道"],"b":[],"z":8},"geometry":{"type":"MultiPolygon","coordinates":[[[[152.92499,56.19222],[152.94337,56.2106],[152.96175,56.19222],[152.94337,56.17383],[152.92499,56.19222]]]]}},{"type":"Feature","properties":{"cs":"21","r":"十勝オホーツク道","rn":"35000202","d":"上り","i":"訓子府ＩＣ付近→訓子府ＩＣ","c":"工事","rd":"１車線規制","a":"情報なし","p":[[152.93559,56.18868]],"l":"f","lo":260,"pd":["十勝オホーツク道"],"b":[],"z":9},"geometry":{"type":"MultiPolygon","coordinates":[[[[152.92499,56.19222],[152.93913,56.20636],[152.95327,56.19222],[152.93913,56.17808],[152.92499,56.19222]]]]}},{"type":"Feature","properties":{"b": [], "c": "工事", "d": "下り", "i": "登別室蘭ＩＣ付近→幌別ＴＮ付近", "l": "t", "p": [[149.5776, 54.47856]], "r": "道央道", "z": 8, "cs": "31", "lo": 310, "pd": ["道央道"], "rd": "第１走行規制", "rn": "10010012"},"geometry":{"type":"MultiPolygon","coordinates":[[[[149.57194,54.5026],[149.59033,54.48422],[149.57194,54.46583],[149.55356,54.48422],[149.57194,54.5026]]]]}},{"type":"Feature","properties":{"b": [], "c": "工事", "d": "下り", "i": "登別室蘭ＩＣ付近→幌別ＴＮ付近", "l": "f", "p": [[149.57477, 54.47715]], "r": "道央道", "z": 9, "cs": "31", "lo": 310, "pd": ["道央道"], "rd": "第１走行規制", "rn": "10010012"},"geometry":{"type":"MultiPolygon","coordinates":[[[[149.56842,54.49764],[149.58537,54.48069],[149.57123,54.46655],[149.55427,54.4835],[149.56842,54.49764]]]]}},{"type":"Feature","properties":{"b": [], "c": "植栽作業", "d": "上り", "i": "虎杖浜ＴＮ付近→虎杖浜ＴＮ入口", "l": "f", "p": [[149.72745, 54.44142]], "r": "道央道", "z": 9, "cs": "31", "lo": 310, "pd": ["道央道"], "rd": "第１走行規制", "rn": "10010015"},"geometry":{"type":"MultiPolygon","coordinates":[[[[149.74513,54.44496],[149.73099,54.43081],[149.71685,54.44496],[149.73099,54.4591],[149.74513,54.44496]]]]}},{"type":"Feature","properties":{"b": [], "c": "植栽作業", "d": "上り", "i": "虎杖浜ＴＮ付近→虎杖浜ＴＮ入口", "l": "t", "p": [[149.72745, 54.43718]], "r": "道央道", "z": 8, "cs": "31", "lo": 310, "pd": ["道央道"], "rd": "第１走行規制", "rn": "10010015"},"geometry":{"type":"MultiPolygon","coordinates":[[[[149.7515,54.44283],[149.73311,54.42445],[149.71473,54.44283],[149.73311,54.46122],[149.7515,54.44283]]]]}},{"type":"Feature","properties":{"b": [], "c": "工事", "d": "上り", "i": "江部乙ＢＳ→江部乙ＢＳ付近", "l": "f", "p": [[150.83537, 56.94278]], "r": "道央道", "z": 9, "cs": "31", "lo": 310, "pd": ["道央道"], "rd": "第１走行規制", "rn": "10015012"},"geometry":{"type":"MultiPolygon","coordinates":[[[[150.85305,56.94632],[150.8389,56.93218],[150.82476,56.94632],[150.8389,56.96046],[150.85305,56.94632]]]]}},{"type":"Feature","properties":{"b": [], "c": "工事", "d": "上り", "i": "江部乙ＢＳ→江部乙ＢＳ付近", "l": "t", "p": [[150.83537, 56.93854]], "r": "道央道", "z": 8, "cs": "31", "lo": 310, "pd": ["道央道"], "rd": "第１走行規制", "rn": "10015012"},"geometry":{"type":"MultiPolygon","coordinates":[[[[150.85941,56.9442],[150.84103,56.92581],[150.82264,56.9442],[150.84103,56.96258],[150.85941,56.9442]]]]}},{"type":"Feature","properties":{"b": [], "c": "工事", "d": "上り", "i": "砂川吉野ＢＳ→奈井江砂川ＩＣ付近", "l": "f", "p": [[150.69706, 56.80447]], "r": "道央道", "z": 9, "cs": "31", "lo": 310, "pd": ["道央道"], "rd": "第１走行規制", "rn": "10015012"},"geometry":{"type":"MultiPolygon","coordinates":[[[[150.71473,56.80801],[150.70059,56.79386],[150.68645,56.80801],[150.70059,56.82215],[150.71473,56.80801]]]]}},{"type":"Feature","properties":{"b": [], "c": "工事", "d": "上り", "i": "砂川吉野ＢＳ→奈井江砂川ＩＣ付近", "l": "t", "p": [[150.69894, 56.80211]], "r": "道央道", "z": 8, "cs": "31", "lo": 310, "pd": ["道央道"], "rd": "第１走行規制", "rn": "10015012"},"geometry":{"type":"MultiPolygon","coordinates":[[[[150.72298,56.80777],[150.70459,56.78938],[150.68621,56.80777],[150.70459,56.82615],[150.72298,56.80777]]]]}},{"type":"Feature","properties":{"b": [], "c": "施設工事", "d": "下り", "i": "深川ＪＣＴ付近→深川ＪＣＴ", "l": "f", "p": [[150.84104, 56.97674]], "r": "道央道", "z": 9, "cs": "31", "lo": 310, "pd": ["道央道"], "rd": "第１走行規制", "rn": "10015015"},"geometry":{"type":"MultiPolygon","coordinates":[[[[150.82336,56.9732],[150.8375,56.98735],[150.85165,56.9732],[150.8375,56.95906],[150.82336,56.9732]]]]}},{"type":"Feature","properties":{"b": [], "c": "舗装工事", "d": "下り", "i": "札幌ＩＣ→札幌ＩＣ付近", "l": "f", "p": [[150.0411, 56.39322]], "r": "道央道", "z": 9, "cs": "31", "lo": 310, "pd": ["道央道"], "rd": "第１走行規制", "rn": "10015015"},"geometry":{"type":"MultiPolygon","coordinates":[[[[150.0261,56.40322],[150.0461,56.40322],[150.0461,56.38322],[150.0261,56.38322],[150.0261,56.40322]]]]}},{"type":"Feature","properties":{"b": [], "c": "舗装工事", "d": "下り", "i": "札幌ＩＣ→札幌ＩＣ付近", "l": "t", "p": [[150.0448, 56.39622]], "r": "道央道", "z": 8, "cs": "31", "lo": 310, "pd": ["道央道"], "rd": "第１走行規制", "rn": "10015015"},"geometry":{"type":"MultiPolygon","coordinates":[[[[150.0238,56.40922],[150.0498,56.40922],[150.0498,56.38322],[150.0238,56.38322],[150.0238,56.40922]]]]}},{"type":"Feature","properties":{"b": [], "c": "橋架補修作業", "d": "下り", "i": "野幌ＰＡ付近→野幌ＰＡ", "l": "f", "p": [[150.15138, 56.39322]], "r": "道央道", "z": 9, "cs": "31", "lo": 310, "pd": ["道央道"], "rd": "第１走行規制", "rn": "10015015"},"geometry":{"type":"MultiPolygon","coordinates":[[[[150.13638,56.40322],[150.15638,56.40322],[150.15638,56.38322],[150.13638,56.38322],[150.13638,56.40322]]]]}},{"type":"Feature","properties":{"b": [], "c": "橋架補修作業", "d": "下り", "i": "野幌ＰＡ付近→野幌ＰＡ", "l": "t", "p": [[150.15438, 56.39622]], "r": "道央道", "z": 8, "cs": "31", "lo": 310, "pd": ["道央道"], "rd": "第１走行規制", "rn": "10015015"},"geometry":{"type":"MultiPolygon","coordinates":[[[[150.13338,56.40922],[150.15938,56.40922],[150.15938,56.38322],[150.13338,56.38322],[150.13338,56.40922]]]]}},{"type":"Feature","properties":{"b": [], "c": "施設工事", "d": "下り", "i": "深川ＪＣＴ付近→深川ＪＣＴ", "l": "t", "p": [[150.83892, 56.97886]], "r": "道央道", "z": 8, "cs": "31", "lo": 310, "pd": ["道央道"], "rd": "第１走行規制", "rn": "10015015"},"geometry":{"type":"MultiPolygon","coordinates":[[[[150.81488,56.9732],[150.83326,56.99159],[150.85165,56.9732],[150.83326,56.95482],[150.81488,56.9732]]]]}},{"type":"Feature","properties":{"b": [], "c": "工事", "d": "下り", "i": "張碓ＴＮ付近", "l": "f", "p": [[149.02721, 56.57302]], "r": "札樽道", "z": 9, "cs": "31", "lo": 310, "pd": ["札樽道"], "rd": "第１走行規制", "rn": "10030012"},"geometry":{"type":"MultiPolygon","coordinates":[[[[149.01221,56.58302],[149.03221,56.58302],[149.03221,56.56302],[149.01221,56.56302],[149.01221,56.58302]]]]}},{"type":"Feature","properties":{"b": [], "c": "工事", "d": "下り", "i": "張碓ＴＮ付近", "l": "t", "p": [[149.03021, 56.57602]], "r": "札樽道", "z": 8, "cs": "31", "lo": 310, "pd": ["札樽道"], "rd": "第１走行規制", "rn": "10030012"},"geometry":{"type":"MultiPolygon","coordinates":[[[[149.00921,56.58902],[149.03521,56.58902],[149.03521,56.56302],[149.00921,56.56302],[149.00921,56.58902]]]]}},{"type":"Feature","properties":{"b": [], "c": "植栽作業", "d": "下り", "i": "朝里ＩＣ→小樽ＪＣＴ", "l": "t", "p": [[148.902, 56.57602]], "r": "札樽道", "z": 8, "cs": "31", "lo": 310, "pd": ["札樽道"], "rd": "第１走行規制", "rn": "10030012"},"geometry":{"type":"MultiPolygon","coordinates":[[[[148.79333,56.56302],[148.79334,56.58902],[148.907,56.589],[148.907,56.563],[148.79333,56.56302]]]]}},{"type":"Feature","properties":{"b": [], "c": "植栽作業", "d": "下り", "i": "朝里ＩＣ→小樽ＪＣＴ", "l": "f", "p": [[148.902, 56.57302]], "r": "札樽道", "z": 9, "cs": "31", "lo": 310, "pd": ["札樽道"], "rd": "第１走行規制", "rn": "10030012"},"geometry":{"type":"MultiPolygon","coordinates":[[[[148.79333,56.56302],[148.79334,56.58302],[148.907,56.583],[148.907,56.563],[148.79333,56.56302]]]]}},{"type":"Feature","properties":{"b": [], "c": "橋架補修作業", "d": "下り", "i": "苫小牧中央ＩＣ付近→苫小牧中央ＩＣ", "l": "t", "p": [[149.93401, 54.69885]], "r": "道央道", "z": 8, "cs": "34", "lo": 340, "pd": ["道央道"], "rd": "追越車線規制", "rn": "10010012"},"geometry":{"type":"MultiPolygon","coordinates":[[[[149.92101,54.68589],[149.92101,54.70385],[149.94701,54.70385],[149.94701,54.67512],[149.92101,54.68589]]]]}},{"type":"Feature","properties":{"b": [], "c": "清掃作業", "d": "下り", "i": "登別東ＩＣ→登別東ＩＣ付近", "l": "t", "p": [[149.72037, 54.46686]], "r": "道央道", "z": 8, "cs": "34", "lo": 340, "pd": ["道央道"], "rd": "追越車線規制", "rn": "10010012"},"geometry":{"type":"MultiPolygon","coordinates":[[[[149.69633,54.4612],[149.71471,54.47959],[149.7331,54.4612],[149.71471,54.44282],[149.69633,54.4612]]]]}},{"type":"Feature","properties":{"b": [], "c": "清掃作業", "d": "下り", "i": "登別東ＩＣ→登別東ＩＣ付近", "l": "f", "p": [[149.71825, 54.4605]], "r": "道央道", "z": 9, "cs": "34", "lo": 340, "pd": ["道央道"], "rd": "追越車線規制", "rn": "10010012"},"geometry":{"type":"MultiPolygon","coordinates":[[[[149.70057,54.45696],[149.71471,54.4711],[149.72885,54.45696],[149.71471,54.44282],[149.70057,54.45696]]]]}},{"type":"Feature","properties":{"b": [], "c": "清掃作業", "d": "下り", "i": "竹浦ＢＳ付近→萩野ＰＡ付近", "l": "f", "p": [[149.7363, 54.47855]], "r": "道央道", "z": 9, "cs": "34", "lo": 340, "pd": ["道央道"], "rd": "追越車線規制", "rn": "10010012"},"geometry":{"type":"MultiPolygon","coordinates":[[[[149.71863,54.47502],[149.73277,54.48916],[149.74691,54.47502],[149.73277,54.46088],[149.71863,54.47502]]]]}},{"type":"Feature","properties":{"b": [], "c": "清掃作業", "d": "下り", "i": "竹浦ＢＳ付近→萩野ＰＡ付近", "l": "t", "p": [[149.73418, 54.48067]], "r": "道央道", "z": 8, "cs": "34", "lo": 340, "pd": ["道央道"], "rd": "追越車線規制", "rn": "10010012"},"geometry":{"type":"MultiPolygon","coordinates":[[[[149.71014,54.47502],[149.72853,54.4934],[149.74691,54.47502],[149.72853,54.45663],[149.71014,54.47502]]]]}},{"type":"Feature","properties":{"b": [], "c": "橋架補修作業", "d": "下り", "i": "苫小牧中央ＩＣ付近→苫小牧中央ＩＣ", "l": "f", "p": [[149.93701, 54.69885]], "r": "道央道", "z": 9, "cs": "34", "lo": 340, "pd": ["道央道"], "rd": "追越車線規制", "rn": "10010012"},"geometry":{"type":"MultiPolygon","coordinates":[[[[149.92701,54.68385],[149.92701,54.70385],[149.94701,54.70385],[149.94701,54.68385],[149.92701,54.68385]]]]}},{"type":"Feature","properties":{"b": [], "c": "橋架補修作業", "d": "上り", "i": "苫小牧中央ＩＣ付近", "l": "t", "p": [[149.96001, 54.6988]], "r": "道央道", "z": 8, "cs": "34", "lo": 340, "pd": ["道央道"], "rd": "追越車線規制", "rn": "10010015"},"geometry":{"type":"MultiPolygon","coordinates":[[[[149.97301,54.76585],[149.97301,54.6938],[149.94701,54.6938],[149.94701,54.76585],[149.97301,54.76585]]]]}},{"type":"Feature","properties":{"b": [], "c": "施設工事", "d": "上り", "i": "札幌南ＩＣ付近", "l": "f", "p": [[149.95701, 55.85345]], "r": "道央道", "z": 9, "cs": "34", "lo": 340, "pd": ["道央道"], "rd": "追越車線規制", "rn": "10010015"},"geometry":{"type":"MultiPolygon","coordinates":[[[[149.96701,55.86845],[149.96701,55.84845],[149.94701,55.84845],[149.94701,55.86845],[149.96701,55.86845]]]]}},{"type":"Feature","properties":{"b": [], "c": "橋架補修作業", "d": "上り", "i": "苫小牧中央ＩＣ付近", "l": "f", "p": [[149.95701, 54.6988]], "r": "道央道", "z": 9, "cs": "34", "lo": 340, "pd": ["道央道"], "rd": "追越車線規制", "rn": "10010015"},"geometry":{"type":"MultiPolygon","coordinates":[[[[149.96701,54.76585],[149.96701,54.6938],[149.94701,54.6938],[149.94701,54.76585],[149.96701,54.76585]]]]}},{"type":"Feature","properties":{"b": [], "c": "施設工事", "d": "上り", "i": "札幌南ＩＣ付近", "l": "t", "p": [[149.96001, 55.85045]], "r": "道央道", "z": 8, "cs": "34", "lo": 340, "pd": ["道央道"], "rd": "追越車線規制", "rn": "10010015"},"geometry":{"type":"MultiPolygon","coordinates":[[[[149.97301,55.87145],[149.97301,55.84545],[149.94701,55.84545],[149.94701,55.87145],[149.97301,55.87145]]]]}},{"type":"Feature","properties":{"b": [], "c": "施設工事", "d": "上り", "i": "江別西ＩＣ→江別西ＩＣ付近", "l": "f", "p": [[150.05556, 56.37322]], "r": "道央道", "z": 9, "cs": "34", "lo": 340, "pd": ["道央道"], "rd": "追越車線規制", "rn": "10015012"},"geometry":{"type":"MultiPolygon","coordinates":[[[[150.07056,56.36322],[150.05056,56.36322],[150.05056,56.38322],[150.07056,56.38322],[150.07056,56.36322]]]]}},{"type":"Feature","properties":{"b": [], "c": "舗装工事", "d": "上り", "i": "栗沢ＢＳ付近→江別東ＩＣ付近", "l": "t", "p": [[150.24147, 56.37022]], "r": "道央道", "z": 8, "cs": "34", "lo": 340, "pd": ["道央道"], "rd": "追越車線規制", "rn": "10015012"},"geometry":{"type":"MultiPolygon","coordinates":[[[[150.27243,56.35722],[150.27243,56.35722],[150.23647,56.35722],[150.23647,56.38322],[150.26166,56.38322],[150.27243,56.35722]]]]}},{"type":"Feature","properties":{"b": [], "c": "橋架補修作業", "d": "上り", "i": "三笠ＩＣ付近→岩見沢ＳＡ付近", "l": "f", "p": [[150.40221, 56.50962]], "r": "道央道", "z": 9, "cs": "34", "lo": 340, "pd": ["道央道"], "rd": "追越車線規制", "rn": "10015012"},"geometry":{"type":"MultiPolygon","coordinates":[[[[150.42943,56.52271],[150.40574,56.49902],[150.3916,56.51316],[150.41529,56.53685],[150.42943,56.52271]]]]}},{"type":"Feature","properties":{"b": [], "c": "橋架補修作業", "d": "上り", "i": "三笠ＩＣ付近→岩見沢ＳＡ付近", "l": "t", "p": [[150.40433, 56.5075]], "r": "道央道", "z": 8, "cs": "34", "lo": 340, "pd": ["道央道"], "rd": "追越車線規制", "rn": "10015012"},"geometry":{"type":"MultiPolygon","coordinates":[[[[150.43368,56.51846],[150.40999,56.49478],[150.3916,56.51316],[150.41529,56.53685],[150.43368,56.51846]]]]}},{"type":"Feature","properties":{"b": [], "c": "舗装工事", "d": "上り", "i": "栗沢ＢＳ付近→江別東ＩＣ付近", "l": "f", "p": [[150.24447, 56.37322]], "r": "道央道", "z": 9, "cs": "34", "lo": 340, "pd": ["道央道"], "rd": "追越車線規制", "rn": "10015012"},"geometry":{"type":"MultiPolygon","coordinates":[[[[150.26994,56.36322],[150.23947,56.36322],[150.23947,56.38322],[150.26166,56.38322],[150.26994,56.36322]]]]}},{"type":"Feature","properties":{"b": [], "c": "橋架補修作業", "d": "上り", "i": "江別東ＩＣ→江別東ＩＣ付近", "l": "f", "p": [[150.18055, 56.37322]], "r": "道央道", "z": 9, "cs": "34", "lo": 340, "pd": ["道央道"], "rd": "追越車線規制", "rn": "10015012"},"geometry":{"type":"MultiPolygon","coordinates":[[[[150.23721,56.36322],[150.17555,56.36322],[150.17555,56.38322],[150.23721,56.38322],[150.23721,56.36322]]]]}},{"type":"Feature","properties":{"b": [], "c": "施設工事", "d": "上り", "i": "江別西ＩＣ→江別西ＩＣ付近", "l": "t", "p": [[150.05018, 56.37022]], "r": "道央道", "z": 8, "cs": "34", "lo": 340, "pd": ["道央道"], "rd": "追越車線規制", "rn": "10015012"},"geometry":{"type":"MultiPolygon","coordinates":[[[[150.07118,56.35722],[150.04518,56.35722],[150.04518,56.38322],[150.07118,56.38322],[150.07118,56.35722]]]]}},{"type":"Feature","properties":{"b": [], "c": "橋架補修作業", "d": "上り", "i": "江別東ＩＣ→江別東ＩＣ付近", "l": "t", "p": [[150.18055, 56.37022]], "r": "道央道", "z": 8, "cs": "34", "lo": 340, "pd": ["道央道"], "rd": "追越車線規制", "rn": "10015012"},"geometry":{"type":"MultiPolygon","coordinates":[[[[150.23721,56.35722],[150.17555,56.35722],[150.17555,56.38322],[150.23721,56.38322],[150.23721,56.35722]]]]}},{"type":"Feature","properties":{"b": [], "c": "トンネル工事", "d": "下り", "i": "美唄ＴＮ入口→美唄ＴＮ出口", "l": "t", "p": [[150.50278, 56.64272]], "r": "道央道", "z": 8, "cs": "34", "lo": 340, "pd": ["道央道"], "rd": "追越車線規制", "rn": "10015015"},"geometry":{"type":"MultiPolygon","coordinates":[[[[150.47874,56.63707],[150.49712,56.65545],[150.51551,56.63707],[150.49712,56.61868],[150.47874,56.63707]]]]}},{"type":"Feature","properties":{"b": [], "c": "トンネル工事", "d": "下り", "i": "美唄ＴＮ入口→美唄ＴＮ出口", "l": "f", "p": [[150.50278, 56.63848]], "r": "道央道", "z": 9, "cs": "34", "lo": 340, "pd": ["道央道"], "rd": "追越車線規制", "rn": "10015015"},"geometry":{"type":"MultiPolygon","coordinates":[[[[150.4851,56.63495],[150.49925,56.64909],[150.51339,56.63495],[150.49925,56.6208],[150.4851,56.63495]]]]}},{"type":"Feature","properties":{"b": [], "c": "橋架補修作業", "d": "下り", "i": "岩見沢ＳＡ→三笠ＩＣ付近", "l": "t", "p": [[150.39899, 56.53894]], "r": "道央道", "z": 8, "cs": "34", "lo": 340, "pd": ["道央道"], "rd": "追越車線規制", "rn": "10015015"},"geometry":{"type":"MultiPolygon","coordinates":[[[[150.35762,56.51595],[150.39334,56.55167],[150.41172,56.53328],[150.37601,56.49756],[150.35762,56.51595]]]]}},{"type":"Feature","properties":{"b": [], "c": "橋架補修作業", "d": "下り", "i": "岩見沢ＳＡ→三笠ＩＣ付近", "l": "f", "p": [[150.40112, 56.53682]], "r": "道央道", "z": 9, "cs": "34", "lo": 340, "pd": ["道央道"], "rd": "追越車線規制", "rn": "10015015"},"geometry":{"type":"MultiPolygon","coordinates":[[[[150.36186,56.51171],[150.39758,56.54742],[150.41172,56.53328],[150.37601,56.49756],[150.36186,56.51171]]]]}},{"type":"Feature","properties":{"b": [], "c": "橋架補修作業", "d": "下り", "i": "野幌ＰＡ付近→江別東ＩＣ", "l": "t", "p": [[150.23375, 56.39622]], "r": "道央道", "z": 8, "cs": "34", "lo": 340, "pd": ["道央道"], "rd": "追越車線規制", "rn": "10015015"},"geometry":{"type":"MultiPolygon","coordinates":[[[[150.17262,56.40922],[150.23875,56.40922],[150.23875,56.38322],[150.17262,56.38322],[150.17262,56.40922]]]]}},{"type":"Feature","properties":{"b": [], "c": "橋架補修作業", "d": "下り", "i": "野幌ＰＡ付近→江別東ＩＣ", "l": "f", "p": [[150.23375, 56.39322]], "r": "道央道", "z": 9, "cs": "34", "lo": 340, "pd": ["道央道"], "rd": "追越車線規制", "rn": "10015015"},"geometry":{"type":"MultiPolygon","coordinates":[[[[150.17262,56.40322],[150.23875,56.40322],[150.23875,56.38322],[150.17262,56.38322],[150.17262,56.40322]]]]}},{"type":"Feature","properties":{"b": [], "c": "施設工事", "d": "下り", "i": "札幌西ＩＣ付近→新川ＩＣ付近", "l": "f", "p": [[149.51857, 56.57302]], "r": "札樽道", "z": 9, "cs": "34", "lo": 340, "pd": ["札樽道"], "rd": "追越車線規制", "rn": "10030012"},"geometry":{"type":"MultiPolygon","coordinates":[[[[149.50307,56.58302],[149.52357,56.58302],[149.52357,56.56302],[149.50307,56.56302],[149.50307,56.58302]]]]}},{"type":"Feature","properties":{"b": [], "c": "施設工事", "d": "下り", "i": "札幌西ＩＣ付近→新川ＩＣ付近", "l": "t", "p": [[149.52132, 56.57602]], "r": "札樽道", "z": 8, "cs": "34", "lo": 340, "pd": ["札樽道"], "rd": "追越車線規制", "rn": "10030012"},"geometry":{"type":"MultiPolygon","coordinates":[[[[149.50032,56.58902],[149.52632,56.58902],[149.52632,56.56302],[149.50032,56.56302],[149.50032,56.58902]]]]}},{"type":"Feature","properties":{"b": [], "c": "トンネル工事", "d": "上り", "i": "朝里ＩＣ→小樽ＩＣ", "l": "f", "p": [[148.67093, 56.55302]], "r": "札樽道", "z": 9, "cs": "34", "lo": 340, "pd": ["札樽道"], "rd": "追越車線規制", "rn": "10030015"},"geometry":{"type":"MultiPolygon","coordinates":[[[[148.78015,56.56302],[148.78015,56.54302],[148.66593,56.54302],[148.66593,56.56302],[148.78015,56.56302]]]]}},{"type":"Feature","properties":{"b": [], "c": "トンネル工事", "d": "上り", "i": "朝里ＩＣ→小樽ＩＣ", "l": "t", "p": [[148.67093, 56.55002]], "r": "札樽道", "z": 8, "cs": "34", "lo": 340, "pd": ["札樽道"], "rd": "追越車線規制", "rn": "10030015"},"geometry":{"type":"MultiPolygon","coordinates":[[[[148.78015,56.56302],[148.78015,56.53702],[148.66593,56.53702],[148.66593,56.56302],[148.78015,56.56302]]]]}},{"type":"Feature","properties":{"b": [], "c": "工事", "d": "下り", "i": "新千歳空港ＩＣ→千歳ＩＣ付近", "l": "f", "p": [[149.93701, 55.17118]], "r": "道央道", "z": 9, "cs": "36", "lo": 510, "pd": ["道央道"], "rd": "路肩規制", "rn": "10010012"},"geometry":{"type":"MultiPolygon","coordinates":[[[[149.92701,55.15618],[149.92701,55.17618],[149.94701,55.17618],[149.94701,55.15618],[149.92701,55.15618]]]]}},{"type":"Feature","properties":{"b": [], "c": "工事", "d": "下り", "i": "新千歳空港ＩＣ→千歳ＩＣ付近", "l": "t", "p": [[149.93401, 55.17418]], "r": "道央道", "z": 8, "cs": "36", "lo": 510, "pd": ["道央道"], "rd": "路肩規制", "rn": "10010012"},"geometry":{"type":"MultiPolygon","coordinates":[[[[149.92101,55.15318],[149.92101,55.17918],[149.94701,55.17918],[149.94701,55.15318],[149.92101,55.15318]]]]}},{"type":"Feature","properties":{"b": [], "c": "工事", "d": "下り", "i": "森ＩＣ付近", "l": "t", "p": [[148.5044, 54.12154]], "r": "道央道", "z": 8, "cs": "36", "lo": 510, "pd": ["道央道"], "rd": "路肩規制", "rn": "10010012"},"geometry":{"type":"MultiPolygon","coordinates":[[[[148.53484,54.10949],[148.51645,54.0911],[148.49167,54.11589],[148.51006,54.13427],[148.53484,54.10949]]]]}},{"type":"Feature","properties":{"b": [], "c": "工事", "d": "下り", "i": "森ＩＣ付近", "l": "f", "p": [[148.50652, 54.12366]], "r": "道央道", "z": 9, "cs": "36", "lo": 510, "pd": ["道央道"], "rd": "路肩規制", "rn": "10010012"},"geometry":{"type":"MultiPolygon","coordinates":[[[[148.53484,54.10949],[148.52069,54.09535],[148.49591,54.12013],[148.51006,54.13427],[148.53484,54.10949]]]]}},{"type":"Feature","properties":{"b": [], "c": "工事", "d": "上り", "i": "深川ＩＣ付近", "l": "t", "p": [[150.94233, 57.0455]], "r": "道央道", "z": 8, "cs": "36", "lo": 510, "pd": ["道央道"], "rd": "路肩規制", "rn": "10015012"},"geometry":{"type":"MultiPolygon","coordinates":[[[[150.99181,57.07659],[150.94799,57.03277],[150.92961,57.05116],[150.97342,57.09498],[150.99181,57.07659]]]]}},{"type":"Feature","properties":{"b": [], "c": "工事", "d": "上り", "i": "深川ＩＣ付近", "l": "f", "p": [[150.94021, 57.04763]], "r": "道央道", "z": 9, "cs": "36", "lo": 510, "pd": ["道央道"], "rd": "路肩規制", "rn": "10015012"},"geometry":{"type":"MultiPolygon","coordinates":[[[[150.98756,57.08084],[150.94375,57.03702],[150.92961,57.05116],[150.97342,57.09498],[150.98756,57.08084]]]]}},{"type":"Feature","properties":{"b": [], "c": "工事", "d": "下り", "i": "美唄ＩＣ付近", "l": "t", "p": [[150.55192, 56.69186]], "r": "道央道", "z": 8, "cs": "36", "lo": 510, "pd": ["道央道"], "rd": "路肩規制", "rn": "10015015"},"geometry":{"type":"MultiPolygon","coordinates":[[[[150.52357,56.6819],[150.54626,56.70459],[150.56465,56.6862],[150.54196,56.66351],[150.52357,56.6819]]]]}},{"type":"Feature","properties":{"b": [], "c": "植栽作業", "d": "下り", "i": "音江ＰＡ付近→音江ＰＡ", "l": "f", "p": [[151.0244, 57.1601]], "r": "道央道", "z": 9, "cs": "36", "lo": 510, "pd": ["道央道"], "rd": "路肩規制", "rn": "10015015"},"geometry":{"type":"MultiPolygon","coordinates":[[[[151.00672,57.15657],[151.02087,57.17071],[151.03501,57.15657],[151.02087,57.14242],[151.00672,57.15657]]]]}},{"type":"Feature","properties":{"b": [], "c": "植栽作業", "d": "下り", "i": "比布ＪＣＴ付近", "l": "t", "p": [[151.12518, 57.62489]], "r": "道央道", "z": 8, "cs": "36", "lo": 510, "pd": ["道央道"], "rd": "路肩規制", "rn": "10015015"},"geometry":{"type":"MultiPolygon","coordinates":[[[[151.13818,57.60389],[151.11218,57.60389],[151.11218,57.62989],[151.13818,57.62989],[151.13818,57.60389]]]]}},{"type":"Feature","properties":{"b": [], "c": "植栽作業", "d": "下り", "i": "音江ＰＡ付近→音江ＰＡ", "l": "t", "p": [[151.0244, 57.16434]], "r": "道央道", "z": 8, "cs": "36", "lo": 510, "pd": ["道央道"], "rd": "路肩規制", "rn": "10015015"},"geometry":{"type":"MultiPolygon","coordinates":[[[[151.00036,57.15869],[151.01874,57.17707],[151.03713,57.15869],[151.01874,57.1403],[151.00036,57.15869]]]]}},{"type":"Feature","properties":{"b": [], "c": "植栽作業", "d": "下り", "i": "比布ＪＣＴ付近", "l": "f", "p": [[151.12818, 57.62146]], "r": "道央道", "z": 9, "cs": "36", "lo": 510, "pd": ["道央道"], "rd": "路肩規制", "rn": "10015015"},"geometry":{"type":"MultiPolygon","coordinates":[[[[151.13818,57.60646],[151.11818,57.60646],[151.11818,57.62646],[151.13818,57.62646],[151.13818,57.60646]]]]}},{"type":"Feature","properties":{"b": [], "c": "工事", "d": "下り", "i": "美唄ＩＣ付近", "l": "f", "p": [[150.55404, 56.68974]], "r": "道央道", "z": 9, "cs": "36", "lo": 510, "pd": ["道央道"], "rd": "路肩規制", "rn": "10015015"},"geometry":{"type":"MultiPolygon","coordinates":[[[[150.52781,56.67766],[150.5505,56.70035],[150.56465,56.6862],[150.54196,56.66351],[150.52781,56.67766]]]]}},{"type":"Feature","properties":{"b": [], "c": "工事", "d": "下り", "i": "見晴ＢＳ付近", "l": "f", "p": [[149.07255, 56.57302]], "r": "札樽道", "z": 9, "cs": "36", "lo": 510, "pd": ["札樽道"], "rd": "路肩規制", "rn": "10030012"},"geometry":{"type":"MultiPolygon","coordinates":[[[[149.05755,56.58302],[149.07755,56.58302],[149.07755,56.56302],[149.05755,56.56302],[149.05755,56.58302]]]]}},{"type":"Feature","properties":{"b": [], "c": "工事", "d": "下り", "i": "見晴ＢＳ付近", "l": "t", "p": [[149.07535, 56.57602]], "r": "札樽道", "z": 8, "cs": "36", "lo": 510, "pd": ["札樽道"], "rd": "路肩規制", "rn": "10030012"},"geometry":{"type":"MultiPolygon","coordinates":[[[[149.05435,56.58902],[149.08035,56.58902],[149.08035,56.56302],[149.05435,56.56302],[149.05435,56.58902]]]]}},{"type":"Feature","properties":{"b": [], "c": "施設工事", "d": "上り", "i": "本別ＪＣＴ付近", "l": "t", "p": [[152.50755, 55.41928]], "r": "道東道", "z": 8, "cs": "36", "lo": 510, "pd": ["道東道"], "rd": "路肩規制", "rn": "10050012"},"geometry":{"type":"MultiPolygon","coordinates":[[[[152.5026,55.4327],[152.52383,55.4327],[152.5316,55.42493],[152.51321,55.40655],[152.49483,55.42493],[152.5026,55.4327],[152.5026,55.4327]]]]}},{"type":"Feature","properties":{"b": [], "c": "施設工事", "d": "上り", "i": "池田ＩＣ・本別ＪＣＴ間付近", "l": "t", "p": [[152.42818, 55.3399]], "r": "道東道", "z": 8, "cs": "36", "lo": 510, "pd": ["道東道"], "rd": "路肩規制", "rn": "10050012"},"geometry":{"type":"MultiPolygon","coordinates":[[[[152.46341,55.35674],[152.43003,55.32337],[152.41926,55.34937],[152.44502,55.37513],[152.46341,55.35674]]]]}},{"type":"Feature","properties":{"b": [], "c": "工事", "d": "上り", "i": "夕張ＩＣ→夕張ＩＣ付近", "l": "f", "p": [[150.7922, 55.33937]], "r": "道東道", "z": 9, "cs": "36", "lo": 510, "pd": ["道東道"], "rd": "路肩規制", "rn": "10050012"},"geometry":{"type":"MultiPolygon","coordinates":[[[[150.81199,55.32937],[150.7872,55.32937],[150.7872,55.34937],[150.81199,55.34937],[150.81199,55.32937]]]]}},{"type":"Feature","properties":{"b": [], "c": "工事", "d": "上り", "i": "夕張ＩＣ→夕張ＩＣ付近", "l": "t", "p": [[150.79159, 55.33637]], "r": "道東道", "z": 8, "cs": "36", "lo": 510, "pd": ["道東道"], "rd": "路肩規制", "rn": "10050012"},"geometry":{"type":"MultiPolygon","coordinates":[[[[150.81259,55.32337],[150.78659,55.32337],[150.78659,55.34937],[150.81259,55.34937],[150.81259,55.32337]]]]}},{"type":"Feature","properties":{"b": [], "c": "施設工事", "d": "上り", "i": "池田ＩＣ・本別ＪＣＴ間付近", "l": "f", "p": [[152.43936, 55.35533]], "r": "道東道", "z": 9, "cs": "36", "lo": 510, "pd": ["道東道"], "rd": "路肩規制", "rn": "10050012"},"geometry":{"type":"MultiPolygon","coordinates":[[[[152.45704,55.35886],[152.4429,55.34472],[152.42876,55.35886],[152.4429,55.37301],[152.45704,55.35886]]]]}},{"type":"Feature","properties":{"b": [], "c": "施設工事", "d": "上り", "i": "本別ＪＣＴ付近", "l": "f", "p": [[152.51392, 55.42988]], "r": "道東道", "z": 9, "cs": "36", "lo": 510, "pd": ["道東道"], "rd": "路肩規制", "rn": "10050012"},"geometry":{"type":"MultiPolygon","coordinates":[[[[152.5086,55.4387],[152.52632,55.4387],[152.5316,55.43342],[152.51746,55.41927],[152.50332,55.43342],[152.5086,55.4387],[152.5086,55.4387]]]]}},{"type":"Feature","properties":{"b": [], "c": "工事", "d": "下り", "i": "池田ＩＣ付近", "l": "t", "p": [[152.37801, 55.36237]], "r": "道東道", "z": 8, "cs": "36", "lo": 510, "pd": ["道東道"], "rd": "路肩規制", "rn": "10050015"},"geometry":{"type":"MultiPolygon","coordinates":[[[[152.34055,55.37537],[152.38301,55.37537],[152.38301,55.34937],[152.34055,55.34937],[152.34055,55.37537]]]]}},{"type":"Feature","properties":{"b": [], "c": "工事", "d": "下り", "i": "池田ＩＣ付近", "l": "f", "p": [[152.37801, 55.35937]], "r": "道東道", "z": 9, "cs": "36", "lo": 510, "pd": ["道東道"], "rd": "路肩規制", "rn": "10050015"},"geometry":{"type":"MultiPolygon","coordinates":[[[[152.34055,55.36937],[152.38301,55.36937],[152.38301,55.34937],[152.34055,55.34937],[152.34055,55.36937]]]]}},{"type":"Feature","properties":{"b": [], "c": "施設工事", "d": "下り", "i": "トマムＩＣ・下トマムＴＮ間付近", "l": "t", "p": [[151.34975, 55.36237]], "r": "道東道", "z": 8, "cs": "36", "lo": 510, "pd": ["道東道"], "rd": "路肩規制", "rn": "10050015"},"geometry":{"type":"MultiPolygon","coordinates":[[[[151.32875,55.37537],[151.35475,55.37537],[151.35475,55.34937],[151.32875,55.34937],[151.32875,55.37537]]]]}},{"type":"Feature","properties":{"b": [], "c": "施設工事", "d": "下り", "i": "トマムＩＣ・下トマムＴＮ間付近", "l": "f", "p": [[151.34675, 55.35937]], "r": "道東道", "z": 9, "cs": "36", "lo": 510, "pd": ["道東道"], "rd": "路肩規制", "rn": "10050015"},"geometry":{"type":"MultiPolygon","coordinates":[[[[151.33175,55.36937],[151.35175,55.36937],[151.35175,55.34937],[151.33175,55.34937],[151.33175,55.36937]]]]}},{"type":"Feature","properties":{"b": [], "c": "工事", "d": "下り", "i": "恵庭ＩＣ→輪厚ＰＡ・スマートＩＣ", "l": "f", "p": [[149.93701, 55.6471]], "r": "道央道", "z": 9, "cs": "96", "lo": 820, "pd": ["道央道"], "rd": "その他規制", "rn": "10010012"},"geometry":{"type":"MultiPolygon","coordinates":[[[[149.92701,55.4458],[149.92701,55.6521],[149.94701,55.6521],[149.94701,55.4458],[149.92701,55.4458]]]]}},{"type":"Feature","properties":{"b": [], "c": "工事", "d": "下り", "i": "恵庭ＩＣ→輪厚ＰＡ・スマートＩＣ", "l": "t", "p": [[149.93401, 55.6471]], "r": "道央道", "z": 8, "cs": "96", "lo": 820, "pd": ["道央道"], "rd": "その他規制", "rn": "10010012"},"geometry":{"type":"MultiPolygon","coordinates":[[[[149.92101,55.4458],[149.92101,55.6521],[149.94701,55.6521],[149.94701,55.4458],[149.92101,55.4458]]]]}},{"type":"Feature","properties":{"b": [], "c": "工事", "d": "上り", "i": "岩見沢ＩＣ付近", "l": "f", "p": [[150.2803, 56.38771]], "r": "道央道", "z": 9, "cs": "96", "lo": 820, "pd": ["道央道"], "rd": "その他規制", "rn": "10015012"},"geometry":{"type":"MultiPolygon","coordinates":[[[[150.29798,56.39125],[150.28383,56.37711],[150.26969,56.39125],[150.28383,56.40539],[150.29798,56.39125]]]]}},{"type":"Feature","properties":{"b": [], "c": "工事", "d": "上り", "i": "岩見沢ＩＣ付近", "l": "t", "p": [[150.27058, 56.37375]], "r": "道央道", "z": 8, "cs": "96", "lo": 820, "pd": ["道央道"], "rd": "その他規制", "rn": "10015012"},"geometry":{"type":"MultiPolygon","coordinates":[[[[150.30222,56.38701],[150.27243,56.35722],[150.26166,56.38322],[150.28383,56.40539],[150.30222,56.38701]]]]}},{"type":"Feature","properties":{"b": [], "c": "工事", "d": "上り", "i": "小樽ＪＣＴ付近", "l": "f", "p": [[148.99334, 56.55302]], "r": "札樽道", "z": 9, "cs": "96", "lo": 820, "pd": ["札樽道"], "rd": "その他規制", "rn": "10030015"},"geometry":{"type":"MultiPolygon","coordinates":[[[[149.00834,56.54302],[148.98834,56.54302],[148.98834,56.56302],[149.00834,56.56302],[149.00834,56.54302]]]]}},{"type":"Feature","properties":{"b": [], "c": "工事", "d": "上り", "i": "小樽ＪＣＴ付近", "l": "t", "p": [[148.99334, 56.55002]], "r": "札樽道", "z": 8, "cs": "96", "lo": 820, "pd": ["札樽道"], "rd": "その他規制", "rn": "10030015"},"geometry":{"type":"MultiPolygon","coordinates":[[[[149.01434,56.53702],[148.98834,56.53702],[148.98834,56.56302],[149.01434,56.56302],[149.01434,56.53702]]]]}},{"type": "Feature", "properties": {"b": [], "c": "工事", "d": "上下", "i": "恵庭ＩＣ～恵庭ＩＣ付近", "l": "t", "p": [], "r": "道央道", "z": 8, "cs": "99", "lo": 840, "pd": ["道央道"], "rd": "規制なし", "rn": "10010012"}},{"type":"Feature","properties":{"cs":"70","r":"道央道","rn":"10015015","d":"下り","i":"音江ＰＡ付近","c":"故障車","rd":"規制なし","a":"情報なし","p":[],"l":"f","lo":840,"pd":["道央道"],"b":[],"z":9},"geometry":{"type":"Point","coordinates":[151.02087,57.15657]}},{"type":"Feature","properties":{"cs":"70","r":"道央道","rn":"10015015","d":"下り","i":"音江ＰＡ付近","c":"故障車","rd":"規制なし","a":"情報なし","p":[],"l":"t","lo":840,"pd":["道央道"],"b":[],"z":8},"geometry":{"type":"Point","coordinates":[151.01874,57.15869]}}]}